odoo/addons/energy_communities_service_invoicing/README.md
odoo/addons/energy_communities_service_invoicing/__init__.py
odoo/addons/energy_communities_service_invoicing/__manifest__.py
odoo/addons/energy_communities_service_invoicing/config.py
odoo/addons/energy_communities_service_invoicing/utils.py
odoo/addons/energy_communities_service_invoicing/components/__init__.py
odoo/addons/energy_communities_service_invoicing/components/account_utils.py
odoo/addons/energy_communities_service_invoicing/components/contract_utils.py
odoo/addons/energy_communities_service_invoicing/components/product_utils.py
odoo/addons/energy_communities_service_invoicing/components/sale_order_utils.py
odoo/addons/energy_communities_service_invoicing/data/contract_cron.xml
odoo/addons/energy_communities_service_invoicing/data/contract_line_qty_formula_data.xml
odoo/addons/energy_communities_service_invoicing/data/product_data.xml
odoo/addons/energy_communities_service_invoicing/demo/product_template_demo.xml
odoo/addons/energy_communities_service_invoicing/demo/res_company_demo.xml
odoo/addons/energy_communities_service_invoicing/demo/res_user_demo.xml
odoo/addons/energy_communities_service_invoicing/demo/subscription_request_demo.xml
odoo/addons/energy_communities_service_invoicing/i18n/ca_ES.po
odoo/addons/energy_communities_service_invoicing/i18n/energy_communities_service_invoicing.pot
odoo/addons/energy_communities_service_invoicing/i18n/es.po
odoo/addons/energy_communities_service_invoicing/i18n/eu_ES.po
odoo/addons/energy_communities_service_invoicing/migrations/16.0.0.5.0/post-migration.py
odoo/addons/energy_communities_service_invoicing/migrations/16.0.0.6.0/post-migration.py
odoo/addons/energy_communities_service_invoicing/models/__init__.py
odoo/addons/energy_communities_service_invoicing/models/abstract_contract.py
odoo/addons/energy_communities_service_invoicing/models/account_move.py
odoo/addons/energy_communities_service_invoicing/models/contract.py
odoo_addon_energy_communities_service_invoicing-16.0.0.7.0.dist-info/METADATA
odoo_addon_energy_communities_service_invoicing-16.0.0.7.0.dist-info/WHEEL
odoo_addon_energy_communities_service_invoicing-16.0.0.7.0.dist-info/top_level.txt
odoo_addon_energy_communities_service_invoicing-16.0.0.7.0.dist-info/RECORD
