Metadata-Version: 2.1
Name: odoo-addon-energy_communities_service_invoicing
Version: 16.0.0.7.0
Requires-Python: >=3.10
Requires-Dist: odoo-addon-account_invoice_inter_company>=16.0dev,<16.1dev
Requires-Dist: odoo-addon-base_bank_from_iban>=16.0dev,<16.1dev
Requires-Dist: odoo-addon-contract>=16.0dev,<16.1dev
Requires-Dist: odoo-addon-contract_variable_quantity>=16.0dev,<16.1dev
Requires-Dist: odoo-addon-energy_communities>=16.0dev,<16.1dev
Requires-Dist: odoo-addon-energy_communities_cooperator>=16.0dev,<16.1dev
Requires-Dist: odoo-addon-energy_communities_crm>=16.0dev,<16.1dev
Requires-Dist: odoo-addon-l10n_es_igic>=16.0dev,<16.1dev
Requires-Dist: odoo-addon-product_contract>=16.0dev,<16.1dev
Requires-Dist: odoo-addon-sale_order_metadata>=16.0dev,<16.1dev
Requires-Dist: odoo>=16.0a,<16.1dev
Summary: Short (1 phrase/line) summary of the module's purpose, used as subtitle on modules listing or apps.openerp.com
Home-page: https://git.coopdevs.org/coopdevs/comunitats-energetiques/odoo-ce
Author: Som comunitats
Classifier: Programming Language :: Python
Classifier: Framework :: Odoo
Classifier: Framework :: Odoo :: 16.0
